inspireface-1.8.0.data/purelib/inspireface/__init__.py
inspireface-1.8.0.data/purelib/inspireface/param.py
inspireface-1.8.0.data/purelib/inspireface/modules/__init__.py
inspireface-1.8.0.data/purelib/inspireface/modules/inspireface.py
inspireface-1.8.0.data/purelib/inspireface/modules/core/__init__.py
inspireface-1.8.0.data/purelib/inspireface/modules/core/native.py
inspireface-1.8.0.data/purelib/inspireface/modules/core/libs/linux/x64/libInspireFace.so
inspireface-1.8.0.data/purelib/inspireface/modules/utils/__init__.py
inspireface-1.8.0.data/purelib/inspireface/modules/utils/resource.py
inspireface-1.8.0.data/purelib/test/__init__.py
inspireface-1.8.0.data/purelib/test/test_settings.py
inspireface-1.8.0.data/purelib/test/test_utilis.py
inspireface-1.8.0.data/purelib/test/integration/__init__.py
inspireface-1.8.0.data/purelib/test/performance/__init__.py
inspireface-1.8.0.data/purelib/test/performance/test_lfw_precision.py
inspireface-1.8.0.data/purelib/test/unit/__init__.py
inspireface-1.8.0.data/purelib/test/unit/test_base_module.py
inspireface-1.8.0.data/purelib/test/unit/test_recognition_module.py
inspireface-1.8.0.data/purelib/test/unit/test_tracker_module.py
inspireface-1.8.0.dist-info/METADATA
inspireface-1.8.0.dist-info/WHEEL
inspireface-1.8.0.dist-info/top_level.txt
inspireface-1.8.0.dist-info/RECORD
