Metadata-Version: 2.1
Name: inspireface
Version: 1.8.0
Summary: InspireFace Python SDK
Home-page: https://github.com/HyperInspire/InspireFace
Author: Jingyu Yan
Author-email: tunmxy@163.com
Classifier: Development Status :: 5 - Production/Stable
Classifier: Intended Audience :: Developers
Classifier: License :: OSI Approved :: MIT License
Classifier: Programming Language :: Python :: 3
Classifier: Programming Language :: Python :: 3.7
Classifier: Programming Language :: Python :: 3.8
Classifier: Programming Language :: Python :: 3.9
Classifier: Programming Language :: Python :: 3.10
Classifier: Operating System :: POSIX :: Linux
Classifier: Operating System :: Microsoft :: Windows
Classifier: Operating System :: MacOS :: MacOS X
Requires-Python: >=3.7
Requires-Dist: numpy
Requires-Dist: loguru
